MANIFEST.in
README.md
README.rst
setup.py
scatnetgpu/__init__.py
scatnetgpu/filter_banks.py
scatnetgpu/scatnetgpu.py
scatnetgpu.egg-info/PKG-INFO
scatnetgpu.egg-info/SOURCES.txt
scatnetgpu.egg-info/dependency_links.txt
scatnetgpu.egg-info/not-zip-safe
scatnetgpu.egg-info/requires.txt
scatnetgpu.egg-info/top_level.txt