Metadata-Version: 1.0
Name: scatnetgpu
Version: 1.1
Summary: Scattering Network for Python and CUDA
Home-page: http://github.com/oinegue/scatnetgpu
Author: Eugenio Nurrito
Author-email: eugi90@gmail.com
License: MIT
Platform: UNKNOWN
